ZiCutter/He2Zi.py
ZiCutter/ZiCutter.py
ZiCutter/__init__.py
ZiCutter/HanZi/ChaiZi.txt
ZiCutter/HanZi/HeZi.txt
ZiCutter/HanZi/JiZi.txt
ZiCutter/HanZi/YiTiZi.txt
ZiCutter-0.0.10.dist-info/METADATA
ZiCutter-0.0.10.dist-info/WHEEL
ZiCutter-0.0.10.dist-info/top_level.txt
ZiCutter-0.0.10.dist-info/RECORD
