Metadata-Version: 2.1
Name: ZiCutter
Version: 0.0.10
Summary: ZiCutter: cut character smaller
Home-page: https://github.com/laohur/ZiCutter
Author: laohur
Author-email: laohur@gmail.com
License: [Anti-996 License](https: // github.com/996icu/996.ICU/blob/master/LICENSE)
Keywords: ZiCutter,UnicodeTokenizer,ZiTokenizer,Tokenizer,Unicode,laohur
Requires-Python: >=3.0
Requires-Dist: UnicodeTokenizer
Requires-Dist: logzero
